setup.py
funniest_90893/__init__.py
funniest_90893.egg-info/PKG-INFO
funniest_90893.egg-info/SOURCES.txt
funniest_90893.egg-info/dependency_links.txt
funniest_90893.egg-info/not-zip-safe
funniest_90893.egg-info/top_level.txt